indexed_file/__init__.py
indexed_file/version.py
tests/__init__.py
tests/context.py
tests/test_indexed_file.py
Indexed_File-0.1.2.dist-info/LICENSE
Indexed_File-0.1.2.dist-info/METADATA
Indexed_File-0.1.2.dist-info/WHEEL
Indexed_File-0.1.2.dist-info/top_level.txt
Indexed_File-0.1.2.dist-info/RECORD
